Metadata-Version: 2.1
Name: idlerich
Version: 0.3.0
Summary: A bootloader that caches and auto-richifies IDLE because I felt lazy.
Home-page: https://github.com/CuboidRaptor/idlerich
Author: Cuboid Raptor
Author-email: fanjas112358@gmail.com
License: MIT License
Requires-Python: >=3.6
License-File: LICENSE
